titivillus/__init__.py
titivillus/__main__.py
titivillus/codex.py
titivillus/common.py
titivillus/distance.py
titivillus/ngrams.py
titivillus/stemma.py
titivillus-0.0.1.dist-info/LICENSE
titivillus-0.0.1.dist-info/METADATA
titivillus-0.0.1.dist-info/WHEEL
titivillus-0.0.1.dist-info/entry_points.txt
titivillus-0.0.1.dist-info/top_level.txt
titivillus-0.0.1.dist-info/RECORD
