Metadata-Version: 2.1
Name: titivillus
Version: 0.0.1
Summary: Python package to simulate philological evolution
Home-page: https://github.com/tresoldi/titivillus
Author: Tiago Tresoldi
Author-email: tresoldi@gmail.com
License: MIT
Keywords: random phylogenetic network,philology,simulation
Platform: UNKNOWN
Classifier: License :: OSI Approved :: MIT License
Classifier: Operating System :: OS Independent
Classifier: Programming Language :: Python :: 3
Classifier: Topic :: Software Development :: Libraries
Requires-Python: >=3.8
Requires-Dist: numpy
Requires-Dist: networkx
Requires-Dist: matplotlib
